LICENCE
README.md
setup.py
PYW_WeavexPy.egg-info/PKG-INFO
PYW_WeavexPy.egg-info/SOURCES.txt
PYW_WeavexPy.egg-info/dependency_links.txt
PYW_WeavexPy.egg-info/requires.txt
PYW_WeavexPy.egg-info/top_level.txt
WeavexPy/__init__.py
WeavexPy/_messagebox_.py
WeavexPy/css.py
WeavexPy/desktop.py
WeavexPy/ehtml.py
WeavexPy/obj.py
WeavexPy/script.py
WeavexPy/server.py
WeavexPy/style.py