Metadata-Version: 2.4
Name: PYW-WeavexPy
Version: 0.0.8
Summary: PYW-WeavexPy - 0.0.8 - beta
Author: João Victor
Author-email: serveserviceaplication@gmail.com
License: MIT License
Keywords: PYW-WeavexPy
License-File: LICENCE
Requires-Dist: pywebview
Requires-Dist: flask
Dynamic: author
Dynamic: author-email
Dynamic: description
Dynamic: description-content-type
Dynamic: keywords
Dynamic: license
Dynamic: license-file
Dynamic: requires-dist
Dynamic: summary
